digitalpy/__init__.py
digitalpy/core/IAM/IAM_action_filter_strategy.py
digitalpy/core/IAM/IAM_facade.py
digitalpy/core/IAM/IAM_recipient_filter_strategy.py
digitalpy/core/IAM/__init__.py
digitalpy/core/IAM/base/__init__.py
digitalpy/core/IAM/base/iam_action_mapper.py
digitalpy/core/IAM/configuration/__init__.py
digitalpy/core/IAM/configuration/business_rules/iam_rules.py
digitalpy/core/IAM/configuration/external_action_mapping.ini
digitalpy/core/IAM/configuration/iam_constants.py
digitalpy/core/IAM/configuration/internal_action_mapping.ini
digitalpy/core/IAM/configuration/logging.conf
digitalpy/core/IAM/configuration/manifest.ini
digitalpy/core/IAM/controllers/__init__.py
digitalpy/core/IAM/controllers/iam_filter_controller.py
digitalpy/core/IAM/controllers/iam_group_controller.py
digitalpy/core/IAM/controllers/iam_persistence_controller.py
digitalpy/core/IAM/controllers/iam_users_controller.py
digitalpy/core/IAM/domain/Function.py
digitalpy/core/IAM/domain/Group.py
digitalpy/core/IAM/domain/GroupPermissions.py
digitalpy/core/IAM/domain/Root.py
digitalpy/core/IAM/domain/SystemUser.py
digitalpy/core/IAM/domain/__init__.py
digitalpy/core/IAM/filters/__init__.py
digitalpy/core/IAM/filters/default_action_filter.py
digitalpy/core/IAM/filters/default_recipient_filter.py
digitalpy/core/IAM/model/__init__.py
digitalpy/core/IAM/model/connection.py
digitalpy/core/IAM/persistence/__init__.py
digitalpy/core/IAM/persistence/api_calls.py
digitalpy/core/IAM/persistence/contact.py
digitalpy/core/IAM/persistence/iam_base.py
digitalpy/core/IAM/persistence/permissions.py
digitalpy/core/IAM/persistence/session.py
digitalpy/core/IAM/persistence/session_contact.py
digitalpy/core/IAM/persistence/system_group.py
digitalpy/core/IAM/persistence/system_group_permission.py
digitalpy/core/IAM/persistence/system_user.py
digitalpy/core/IAM/persistence/system_user_groups.py
digitalpy/core/IAM/persistence/user.py
digitalpy/core/__init__.py
digitalpy/core/api/__init__.py
digitalpy-0.3.16.dist-info/LICENSE.md
digitalpy-0.3.16.dist-info/METADATA
digitalpy-0.3.16.dist-info/WHEEL
digitalpy-0.3.16.dist-info/RECORD
